nutribr/__init__.py
nutribr/core.py
nutribr/data/taco.csv
nutribr-0.1.0.dist-info/licenses/LICENSE
nutribr-0.1.0.dist-info/METADATA
nutribr-0.1.0.dist-info/WHEEL
nutribr-0.1.0.dist-info/top_level.txt
nutribr-0.1.0.dist-info/RECORD
