Metadata-Version: 2.4
Name: nutribr
Version: 0.1.0
Summary: Biblioteca de dados nutricionais de alimentos brasileiros baseada na TACO/IBGE
Author-email: Pedro Brito <seuemail@exemplo.com>
License: MIT
Project-URL: Homepage, https://github.com/seuusuario/nutribr
Project-URL: Repository, https://github.com/seuusuario/nutribr
Requires-Python: >=3.8
License-File: LICENSE
Requires-Dist: pandas
Dynamic: license-file
